dimpyu/__init__.py
dimpyu/constants.py
dimpyu/quantity.py
dimpyu/registry.py
dimpyu-0.1.2.dist-info/licenses/LICENSE
dimpyu-0.1.2.dist-info/METADATA
dimpyu-0.1.2.dist-info/WHEEL
dimpyu-0.1.2.dist-info/top_level.txt
dimpyu-0.1.2.dist-info/RECORD
