Metadata-Version: 2.4
Name: dimpyu
Version: 0.1.2
Summary: A lightweight, flexible Python library for handling physical units
Author-email: Edgard Mireles <edgardna47@gmail.com>, Antigravity <bot@antigravity.ai>
Project-URL: Homepage, https://github.com/example/units_lib
Classifier: Programming Language :: Python :: 3
Classifier: License :: OSI Approved :: MIT License
Classifier: Operating System :: OS Independent
Requires-Python: >=3.7
License-File: LICENSE
Requires-Dist: numpy
Dynamic: license-file
